imouse_xp/__init__.py
imouse_xp/api/__init__.py
imouse_xp/api/config_api.py
imouse_xp/api/device_api.py
imouse_xp/api/imouse_api.py
imouse_xp/api/mouse_api.py
imouse_xp/api/pic_api.py
imouse_xp/api/shortcut_api.py
imouse_xp/api/user_api.py
imouse_xp/config/__init__.py
imouse_xp/logs/__init__.py
imouse_xp/logs/logger.py
imouse_xp/models/__init__.py
imouse_xp/models/base_model.py
imouse_xp/models/call_back_model.py
imouse_xp/models/config_model.py
imouse_xp/models/device_model.py
imouse_xp/models/model_utils.py
imouse_xp/models/pic_model.py
imouse_xp/models/shortcut_model.py
imouse_xp/net/__init__.py
imouse_xp/net/base_net.py
imouse_xp/utils/__init__.py
imouse_xp/utils/utils.py
imouse_xp-0.0.7.dist-info/METADATA
imouse_xp-0.0.7.dist-info/WHEEL
imouse_xp-0.0.7.dist-info/top_level.txt
imouse_xp-0.0.7.dist-info/RECORD
