Metadata-Version: 2.4
Name: imouse_xp
Version: 0.0.7
Summary: iMouseXP版本的自动化控制的 Python 包
Home-page: https://github.com/iosauto/py-imouse
Author: iMouse
Author-email: your_email@example.com
Classifier: Programming Language :: Python :: 3
Classifier: License :: OSI Approved :: MIT License
Classifier: Operating System :: OS Independent
Requires-Python: >=3.10
Requires-Dist: annotated-types>=0.7.0
Requires-Dist: certifi>=2024.12.14
Requires-Dist: charset-normalizer>=3.4.1
Requires-Dist: colorlog>=6.9.0
Requires-Dist: idna>=3.10
Requires-Dist: pydantic>=2.10.4
Requires-Dist: pydantic_core>=2.27.2
Requires-Dist: requests>=2.32.3
Requires-Dist: typing_extensions>=4.12.2
Requires-Dist: urllib3>=2.3.0
Requires-Dist: websocket-client>=1.8.0
Requires-Dist: annotated-types>=0.7.0
Dynamic: author
Dynamic: author-email
Dynamic: classifier
Dynamic: description-content-type
Dynamic: home-page
Dynamic: requires-dist
Dynamic: requires-python
Dynamic: summary
